setup.py
b2_storage/__init__.py
b2_storage/backblaze_b2.py
b2_storage/conf.py
b2_storage/storage.py
django_backblazeb2_storage.egg-info/PKG-INFO
django_backblazeb2_storage.egg-info/SOURCES.txt
django_backblazeb2_storage.egg-info/dependency_links.txt
django_backblazeb2_storage.egg-info/top_level.txt