Metadata-Version: 1.1
Name: django-backblazeb2-storage
Version: 0.1
Summary: Django BackBlaze B2 Storage
Home-page: https://github.com/royendgel/django-blackblazeb2-storage
Author: Royendgel Silberie
Author-email: rsilberie@techprocur.com
License: BSD
Platform: UNKNOWN
Classifier: Development Status :: 4 - Beta
Classifier: Environment :: Web Environment
Classifier: Intended Audience :: Developers
Classifier: License :: OSI Approved :: BSD License
Classifier: Operating System :: OS Independent
Classifier: Programming Language :: Python
Classifier: Programming Language :: Python :: 2.7
Classifier: Programming Language :: Python :: 3.3
Classifier: Programming Language :: Python :: 3.4
Classifier: Framework :: Django
